odoo10_addon_hr_holidays_meeting_name-10.0.1.0.0-py2.7-nspkg.pth
odoo/addons/hr_holidays_meeting_name/README.rst
odoo/addons/hr_holidays_meeting_name/__init__.py
odoo/addons/hr_holidays_meeting_name/__manifest__.py
odoo/addons/hr_holidays_meeting_name/models/__init__.py
odoo/addons/hr_holidays_meeting_name/models/hr_holidays.py
odoo/addons/hr_holidays_meeting_name/static/description/icon.png
odoo/addons/hr_holidays_meeting_name/tests/__init__.py
odoo/addons/hr_holidays_meeting_name/tests/test_hr_holidays_meeting_name.py
odoo/addons/hr_holidays_meeting_name/views/hr_holidays_view.xml
odoo10_addon_hr_holidays_meeting_name-10.0.1.0.0.dist-info/DESCRIPTION.rst
odoo10_addon_hr_holidays_meeting_name-10.0.1.0.0.dist-info/METADATA
odoo10_addon_hr_holidays_meeting_name-10.0.1.0.0.dist-info/RECORD
odoo10_addon_hr_holidays_meeting_name-10.0.1.0.0.dist-info/WHEEL
odoo10_addon_hr_holidays_meeting_name-10.0.1.0.0.dist-info/metadata.json
odoo10_addon_hr_holidays_meeting_name-10.0.1.0.0.dist-info/namespace_packages.txt
odoo10_addon_hr_holidays_meeting_name-10.0.1.0.0.dist-info/top_level.txt
